rcfile.py
rcfile-0.1.4.dist-info/DESCRIPTION.rst
rcfile-0.1.4.dist-info/METADATA
rcfile-0.1.4.dist-info/pydist.json
rcfile-0.1.4.dist-info/RECORD
rcfile-0.1.4.dist-info/top_level.txt
rcfile-0.1.4.dist-info/WHEEL
