Metadata-Version: 2.0
Name: rcfile
Version: 0.1.4
Summary: Configuration file loader
Home-page: https://github.com/aequitas/rcfile
Author: Johan Bloemberg
Author-email: mail@ijohan.nl
License: Copyright 2013 Johan Bloemberg
